yogo/__init__.py
yogo/__main__.py
yogo/infer.py
yogo/metrics.py
yogo/model.py
yogo/model_defns.py
yogo/train.py
yogo/yogo_loss.py
yogo/data/__init__.py
yogo/data/blobgen.py
yogo/data/data_transforms.py
yogo/data/dataset_definition_file.py
yogo/data/image_path_dataset.py
yogo/data/split_fractions.py
yogo/data/utils.py
yogo/data/yogo_dataloader.py
yogo/data/yogo_dataset.py
yogo/utils/__init__.py
yogo/utils/argparsers.py
yogo/utils/cluster_anchors.py
yogo/utils/default_hyperparams.py
yogo/utils/export_model.py
yogo/utils/prediction_formatting.py
yogo/utils/test_model.py
yogo/utils/utils.py
yogo-1.0.0.dist-info/LICENSE
yogo-1.0.0.dist-info/METADATA
yogo-1.0.0.dist-info/WHEEL
yogo-1.0.0.dist-info/entry_points.txt
yogo-1.0.0.dist-info/top_level.txt
yogo-1.0.0.dist-info/RECORD
