Metadata-Version: 2.1
Name: yogo
Version: 1.0.0
Summary: The "you only glance once" object detection model
Author-email: Axel Jacobsen <axelnj44@gmail.com>, Paul Lebel <paul.lebel@czbiohub.org>, Ilakkiyan Jeyakumar <ilakkiyan.jeyakumar@czbiohub.org>
License: BSD 3-Clause License
Project-URL: repository, https://github.com/czbiohub-sf/yogo
Keywords: object detection,YOGO,YOLO,deep learning,PyTorch
Requires-Python: <3.11,>=3.9
License-File: LICENSE
Requires-Dist: zarr ==2.17
Requires-Dist: torch <=2.1.0,>=1.13.1
Requires-Dist: torchmetrics[detection] >=0.11.4
Requires-Dist: torchvision >=0.14.1
Requires-Dist: ruamel.yaml ==0.17.21
Requires-Dist: tqdm <5.0.0,>=4.61.2
Requires-Dist: wandb >=0.14.2
Requires-Dist: matplotlib <4.0.0,>=3.4.2
Requires-Dist: MonkeyType ==23.3.0
Requires-Dist: onnx >=1.14.0
Requires-Dist: onnxruntime >=1.14.1
Requires-Dist: onnx-simplifier >=0.4.17
Requires-Dist: openvino-dev ==2023.0.2
Provides-Extra: dev
Requires-Dist: pytest <8.0.0,>=7.4.3 ; extra == 'dev'
Requires-Dist: ruff >=0.4.4 ; extra == 'dev'
Requires-Dist: black >=24.4.2 ; extra == 'dev'
Requires-Dist: mypy >=1.10.0 ; extra == 'dev'
